scikit_lr-0.2.0.dist-info/COPYING
scikit_lr-0.2.0.dist-info/METADATA
scikit_lr-0.2.0.dist-info/RECORD
scikit_lr-0.2.0.dist-info/top_level.txt
scikit_lr-0.2.0.dist-info/WHEEL
sklr/__init__.py
sklr/_types.pxd
sklr/base.py
sklr/consensus.cpython-37m-darwin.so
sklr/consensus.pxd
sklr/exceptions.py
sklr/setup.py
sklr/_build_utils/__init__.py
sklr/datasets/__init__.py
sklr/datasets/_base.py
sklr/datasets/setup.py
sklr/datasets/data/label_ranking/ranks/authorship.csv
sklr/datasets/data/label_ranking/ranks/bodyfat.csv
sklr/datasets/data/label_ranking/ranks/calhousing.csv
sklr/datasets/data/label_ranking/ranks/cold.csv
sklr/datasets/data/label_ranking/ranks/cpu.csv
sklr/datasets/data/label_ranking/ranks/diau.csv
sklr/datasets/data/label_ranking/ranks/dtt.csv
sklr/datasets/data/label_ranking/ranks/elevators.csv
sklr/datasets/data/label_ranking/ranks/fried.csv
sklr/datasets/data/label_ranking/ranks/glass.csv
sklr/datasets/data/label_ranking/ranks/heat.csv
sklr/datasets/data/label_ranking/ranks/housing.csv
sklr/datasets/data/label_ranking/ranks/iris.csv
sklr/datasets/data/label_ranking/ranks/pendigits.csv
sklr/datasets/data/label_ranking/ranks/segment.csv
sklr/datasets/data/label_ranking/ranks/spo.csv
sklr/datasets/data/label_ranking/ranks/stock.csv
sklr/datasets/data/label_ranking/ranks/vehicle.csv
sklr/datasets/data/label_ranking/ranks/vowel.csv
sklr/datasets/data/label_ranking/ranks/wine.csv
sklr/datasets/data/label_ranking/ranks/wisconsin.csv
sklr/datasets/data/partial_label_ranking/probs/authorship.csv
sklr/datasets/data/partial_label_ranking/probs/blocks.csv
sklr/datasets/data/partial_label_ranking/probs/breast.csv
sklr/datasets/data/partial_label_ranking/probs/ecoli.csv
sklr/datasets/data/partial_label_ranking/probs/glass.csv
sklr/datasets/data/partial_label_ranking/probs/iris.csv
sklr/datasets/data/partial_label_ranking/probs/letter.csv
sklr/datasets/data/partial_label_ranking/probs/libras.csv
sklr/datasets/data/partial_label_ranking/probs/pendigits.csv
sklr/datasets/data/partial_label_ranking/probs/satimage.csv
sklr/datasets/data/partial_label_ranking/probs/segment.csv
