Metadata-Version: 2.1
Name: scikit-lr
Version: 0.2.0
Summary: A set of Python modules for Label Ranking problems.
Home-page: https://github.com/alfaro96/scikit-lr
Maintainer: Juan Carlos Alfaro Jiménez
Maintainer-email: JuanCarlos.Alfaro@uclm.es
License: MIT
Download-URL: https://pypi.org/project/scikit-lr/#files
Project-URL: Bug Tracker, https://github.com/alfaro96/scikit-lr/issues
Project-URL: Source Code, https://github.com/alfaro96/scikit-lr
Project-URL: Docker, https://github.com/alfaro96/docker-scikit-lr
Platform: UNKNOWN
Classifier: Development Status :: 5 - Production/Stable
Classifier: Intended Audience :: Education
Classifier: Intended Audience :: Science/Research
Classifier: License :: OSI Approved :: MIT License
Classifier: Natural Language :: English
Classifier: Operating System :: MacOS :: MacOS X
Classifier: Operating System :: POSIX :: Linux
Classifier: Operating System :: Unix
Classifier: Programming Language :: C
Classifier: Programming Language :: C++
Classifier: Programming Language :: Cython
Classifier: Programming Language :: Python :: 3.6
Classifier: Programming Language :: Python :: 3.7
Classifier: Programming Language :: Python :: Implementation :: CPython
Classifier: Topic :: Scientific/Engineering :: Artificial Intelligence
Requires-Dist: numpy (>=1.15.2)
Requires-Dist: scipy (>=1.1.0)
